./.gitignore
./PKG-INFO
./README.md
./pyproject.toml
./hiagent_api/__init__.py
./hiagent_api/base.py
./hiagent_api/chat.py
./hiagent_api/chat_types.py
./hiagent_api/eva.py
./hiagent_api/eva_types.py
./hiagent_api/knowledgebase.py
./hiagent_api/knowledgebase_types.py
./hiagent_api/observe.py
./hiagent_api/observe_types.py
./hiagent_api/tool.py
./hiagent_api/tool_types.py
./hiagent_api/up.py
./hiagent_api/up_types.py
./hiagent_api/workflow.py
./hiagent_api/workflow_types.py
hiagent_api-2.4.0.dist-info/METADATA
hiagent_api-2.4.0.dist-info/WHEEL
hiagent_api-2.4.0.dist-info/RECORD
