Metadata-Version: 2.4
Name: hiagent-api
Version: 2.4.0
Summary: Add your description here
Requires-Python: >=3.10
Requires-Dist: aiofiles>=23.1.0
Requires-Dist: httpx-sse>=0.4.0
Requires-Dist: httpx>=0.28.1
Requires-Dist: pydantic>=2.11.5
Requires-Dist: python-dotenv>=1.1.0
Requires-Dist: strenum>=0.4.15
Requires-Dist: volcengine>=1.0.187
